vindauga/__init__.py
vindauga/timers.py
vindauga/constants/__init__.py
vindauga/constants/buttons.py
vindauga/constants/colors.py
vindauga/constants/command_codes.py
vindauga/constants/drag_flags.py
vindauga/constants/edit_command_codes.py
vindauga/constants/event_codes.py
vindauga/constants/grow_flags.py
vindauga/constants/help_contexts.py
vindauga/constants/key_mappings.py
vindauga/constants/keys.py
vindauga/constants/message_flags.py
vindauga/constants/option_flags.py
vindauga/constants/scrollbar_codes.py
vindauga/constants/state_flags.py
vindauga/constants/std_dialog_commands.py
vindauga/constants/validation_constants.py
vindauga/constants/window_flags.py
vindauga/dialogs/__init__.py
vindauga/dialogs/calculator_dialog.py
vindauga/dialogs/calendar.py
vindauga/dialogs/change_dir_dialog.py
vindauga/dialogs/color_dialog.py
vindauga/dialogs/file_dialog.py
vindauga/dialogs/grid_view_dialog.py
vindauga/dialogs/input_box.py
vindauga/dialogs/message_box.py
vindauga/dialogs/mouse_dialog.py
vindauga/events/__init__.py
vindauga/events/char_scan_type.py
vindauga/events/event.py
vindauga/events/event_queue.py
vindauga/events/key_down_event.py
vindauga/events/message_event.py
vindauga/events/modded_key_codes.py
vindauga/events/mouse_event.py
vindauga/gadgets/__init__.py
vindauga/gadgets/calculator.py
vindauga/gadgets/calendar.py
vindauga/gadgets/puzzle.py
vindauga/help/__init__.py
vindauga/help/cross_reference_node.py
vindauga/help/ref_table.py
vindauga/help/reference.py
vindauga/help/topic_definition.py
vindauga/history_support/__init__.py
vindauga/history_support/history_utils.py
vindauga/menus/__init__.py
vindauga/menus/menu.py
vindauga/menus/menu_bar.py
vindauga/menus/menu_box.py
vindauga/menus/menu_item.py
vindauga/menus/menu_popup.py
vindauga/menus/menu_view.py
vindauga/menus/sub_menu.py
vindauga/mouse/__init__.py
vindauga/mouse/mouse.py
vindauga/terminal/__init__.py
vindauga/terminal/terminal.py
vindauga/terminal/terminal_view.py
vindauga/terminal/terminal_window.py
vindauga-0.5.1.dist-info/LICENSE
vindauga-0.5.1.dist-info/METADATA
vindauga-0.5.1.dist-info/WHEEL
vindauga-0.5.1.dist-info/top_level.txt
vindauga-0.5.1.dist-info/RECORD
