Metadata-Version: 2.1
Name: vindauga
Version: 0.5.1
Summary: Cross Platform Text UI library
Home-page: https://github.com/gabbpuy/vindauga
Author: Andrew Milton
Author-email: vindauga@unyx.net
License: BSD
Platform: UNKNOWN
Classifier: Programming Language :: Python :: 3
Classifier: License :: OSI Approved :: BSD License
Classifier: Operating System :: OS Independent
License-File: LICENSE
Requires-Dist: Pillow>=10.0.0
Requires-Dist: pyperclip>=1.8.2
Requires-Dist: wcwidth>=0.2.6
Requires-Dist: pywin32>=304; sys_platform == "win32"
